uart_tx.v
module uart_tx (
    input clk,
    input rst,
    input start,
    input [7:0] data_in,
    output reg tx,
    output reg busy
);

    parameter CLK_PER_BIT = 87; // For 115200 baud at 10MHz clock

    reg [3:0] bit_index = 0;
    reg [15:0] clk_count = 0;
    reg [9:0] tx_shift = 10'b1111111111;
    reg sending = 0;

    always @(posedge clk or posedge rst) begin
        if (rst) begin
            tx <= 1;
            busy <= 0;
            clk_count <= 0;
            bit_index <= 0;
            tx_shift <= 10'b1111111111;
            sending <= 0;
        end else begin
            if (start && !busy) begin
                // Load frame: start(0), data, stop(1)
                tx_shift <= {1'b1, data_in, 1'b0}; 
                busy <= 1;
                sending <= 1;
                clk_count <= 0;
                bit_index <= 0;
            end else if (sending) begin
                if (clk_count < CLK_PER_BIT - 1) begin
                    clk_count <= clk_count + 1;
                end else begin
                    clk_count <= 0;
                    tx <= tx_shift[bit_index];
                    bit_index <= bit_index + 1;

                    if (bit_index == 9) begin
                        sending <= 0;
                        busy <= 0;
                        tx <= 1;
                    end
                end
            end
        end
    end
endmodule

uart_to_spi_bridge.v
module uart_to_spi_bridge (
    input clk,
    input rst,

    // UART Receiver interface
    input uart_done,
    input [7:0] uart_data,

    // SPI Master interface
    input spi_done,
    input [7:0] spi_rx_data,
    output reg spi_start,
    output reg [7:0] spi_tx_data,

    // UART Transmitter
    output reg tx_start,
    output reg [7:0] tx_data,
    input tx_busy
);

    // Verilog-style state definition
    reg [1:0] state;
    reg [1:0] next_state;

    localparam IDLE      = 2'd0;
    localparam SEND_SPI  = 2'd1;
    localparam WAIT_SPI  = 2'd2;
    localparam SEND_UART = 2'd3;

    always @(posedge clk or posedge rst) begin
        if (rst) begin
            state <= IDLE;
            spi_start <= 0;
            tx_start <= 0;
        end else begin
            state <= next_state;

            // Control signals
            case (next_state)
                IDLE: begin
                    spi_start <= 0;
                    tx_start <= 0;
                end
                SEND_SPI: begin
                    spi_start <= 1;
                    tx_start <= 0;
                end
                WAIT_SPI: begin
                    spi_start <= 0;
                end
                SEND_UART: begin
                    if (!tx_busy)
                        tx_start <= 1;
                end
            endcase
        end
    end

    always @(*) begin
        next_state = state;
        case (state)
            IDLE: if (uart_done)
                      next_state = SEND_SPI;
            SEND_SPI: next_state = WAIT_SPI;
            WAIT_SPI: if (spi_done)
                          next_state = SEND_UART;
            SEND_UART: if (!tx_busy)
                           next_state = IDLE;
        endcase
    end

    always @(posedge clk) begin
        if (uart_done)
            spi_tx_data <= uart_data;

        if (spi_done)
            tx_data <= spi_rx_data;
    end

endmodule

spi_master_slave.v


`timescale 1ns / 1ps

module spi_master (
    input clk,
    input rst,
    input start,
    input [7:0] mosi_data_in,
    output reg [7:0] miso_data_out,
    output reg done,
    output reg sclk,
    output reg mosi,
    input miso,
    output reg cs
);

    reg [2:0] bit_cnt;
    reg [7:0] shift_reg_tx, shift_reg_rx;
    reg [2:0] state;
    reg [1:0] clk_div;

    localparam IDLE = 0,
               ASSERT_CS = 1,
               TRANSFER = 2,
               DEASSERT_CS = 3,
               DONE = 4;

    always @(posedge clk or posedge rst) begin
        if (rst) begin
            state <= IDLE;
            bit_cnt <= 0;
            shift_reg_tx <= 0;
            shift_reg_rx <= 0;
            mosi <= 0;
            sclk <= 0;
            cs <= 1;
            done <= 0;
            miso_data_out <= 0;
            clk_div <= 0;
        end else begin
            clk_div <= clk_div + 1;
            case (state)
                IDLE: begin
                    done <= 0;
                    sclk <= 0;
                    cs <= 1;
                    if (start) begin
                        shift_reg_tx <= mosi_data_in;
                        bit_cnt <= 7;
                        cs <= 0;
                        clk_div <= 0;
                        state <= ASSERT_CS;
                    end
                end
                ASSERT_CS: begin
                    state <= TRANSFER;
                end
                TRANSFER: begin
                    if (clk_div == 2'b11) begin
                        sclk <= ~sclk;

                        if (sclk == 0) begin
                            
                            mosi <= shift_reg_tx[bit_cnt];
                        end else begin
                            
                            shift_reg_rx[bit_cnt] <= miso;
                            if (bit_cnt == 0) begin
                                state <= DEASSERT_CS;
                            end else begin
                                bit_cnt <= bit_cnt - 1;
                            end
                        end
                    end
                end
                DEASSERT_CS: begin
                    cs <= 1;
                    miso_data_out <= shift_reg_rx;
                    state <= DONE;
                end
                DONE: begin
                    done <= 1;
                    state <= IDLE;
                end
            endcase
        end
    end
endmodule


module spi_slave (
    input clk,
    input rst,
    input sclk,
    input mosi,
    output reg miso,
    input cs,
    output reg [7:0] data_out
);

    reg [7:0] shift_reg_rx = 0;
    reg [7:0] shift_reg_tx = 8'hA5;
    reg [2:0] bit_cnt = 0;

    always @(posedge sclk or posedge rst) begin
        if (rst) begin
            shift_reg_rx <= 0;
            data_out <= 0;
            bit_cnt <= 0;
            miso <= 0;
        end else if (!cs) begin
            shift_reg_rx[bit_cnt] <= mosi;
            miso <= shift_reg_tx[bit_cnt];
            if (bit_cnt == 7) begin
                data_out <= shift_reg_rx;
                bit_cnt <= 0;
            end else begin
                bit_cnt <= bit_cnt + 1;
            end
        end
    end
endmodule

uart_rx.v
module uart_rx (
    input clk,
    input rst,
    input rx,
    output reg [7:0] data_out,
    output reg done
);

    parameter CLK_PER_BIT = 87;

    reg [15:0] clk_count = 0;
    reg [3:0] bit_index = 0;
    reg [7:0] rx_shift = 0;
    reg receiving = 0;

    localparam IDLE = 0,
               START = 1,
               DATA = 2,
               STOP = 3;

    reg [1:0] state = IDLE;

    always @(posedge clk or posedge rst) begin
        if (rst) begin
            state <= IDLE;
            clk_count <= 0;
            bit_index <= 0;
            rx_shift <= 0;
            data_out <= 0;
            done <= 0;
        end else begin
            case (state)
                IDLE: begin
                    done <= 0;
                    if (rx == 0) begin // Start bit detected
                        clk_count <= CLK_PER_BIT / 2;
                        state <= START;
                    end
                end
                START: begin
                    if (clk_count == 0) begin
                        state <= DATA;
                        clk_count <= CLK_PER_BIT - 1;
                        bit_index <= 0;
                    end else begin
                        clk_count <= clk_count - 1;
                    end
                end
                DATA: begin
                    if (clk_count == 0) begin
                        rx_shift[bit_index] <= rx;
                        bit_index <= bit_index + 1;
                        if (bit_index == 7) begin
                            state <= STOP;
                        end
                        clk_count <= CLK_PER_BIT - 1;
                    end else begin
                        clk_count <= clk_count - 1;
                    end
                end
                STOP: begin
                    if (clk_count == 0) begin
                        data_out <= rx_shift;
                        done <= 1;
                        state <= IDLE;
                    end else begin
                        clk_count <= clk_count - 1;
                    end
                end
            endcase
        end
    end
endmodule

uart_spi_testbench.v
`timescale 1ns/1ps

module uart_spi_testbench;

    reg clk = 0;
    reg rst = 1;
    reg uart_rx_line = 1;

    // Clock: 10 MHz
    always #50 clk = ~clk;

    // TX controller
    reg start_uart_tx = 0;
    reg [7:0] uart_tx_data = 8'h3C; // Example byte

    wire tx_busy;
    wire uart_tx_line;
    wire uart_done_rx;
    wire [7:0] uart_data_rx;
    wire [7:0] spi_miso_data;
    wire [7:0] slave_data_out;

    // Instantiate UART transmitter to simulate PC sender
    uart_tx #(.CLK_PER_BIT(87)) uart_sender (
        .clk(clk),
        .rst(rst),
        .start(start_uart_tx),
        .data_in(uart_tx_data),
        .tx(uart_tx_line),
        .busy(tx_busy)
    );

    // Connect transmitter to receiver line (loopback)
    always @(posedge clk)
        uart_rx_line <= uart_tx_line;

    // UART Receiver (Bridge input)
    uart_rx #(.CLK_PER_BIT(87)) uart_receiver (
        .clk(clk),
        .rst(rst),
        .rx(uart_rx_line),
        .data_out(uart_data_rx),
        .done(uart_done_rx)
    );

    // SPI Master
    wire spi_start;
    wire spi_done;
    wire [7:0] spi_tx_data;
    wire [7:0] spi_rx_data;
    wire sclk, mosi, miso, cs;

    spi_master spi_master_inst (
        .clk(clk),
        .rst(rst),
        .start(spi_start),
        .mosi_data_in(spi_tx_data),
        .miso_data_out(spi_rx_data),
        .done(spi_done),
        .sclk(sclk),
        .mosi(mosi),
        .miso(miso),
        .cs(cs)
    );

    // SPI Slave
    spi_slave spi_slave_inst (
        .clk(clk),
        .rst(rst),
        .sclk(sclk),
        .mosi(mosi),
        .miso(miso),
        .cs(cs),
        .data_out(slave_data_out)
    );

    // UART-to-SPI Bridge
    wire tx_start;
    wire [7:0] tx_data;
    wire tx_line;

    uart_to_spi_bridge bridge (
        .clk(clk),
        .rst(rst),
        .uart_done(uart_done_rx),
        .uart_data(uart_data_rx),
        .spi_done(spi_done),
        .spi_rx_data(spi_rx_data),
        .spi_start(spi_start),
        .spi_tx_data(spi_tx_data),
        .tx_start(tx_start),
        .tx_data(tx_data),
        .tx_busy(tx_busy)
    );

    // Dummy receiver to complete TX circuit
    uart_tx #(.CLK_PER_BIT(87)) uart_echo (
        .clk(clk),
        .rst(rst),
        .start(tx_start),
        .data_in(tx_data),
        .tx(tx_line),
        .busy(tx_busy)
    );

    initial begin
        $dumpfile("wave.vcd");
        $dumpvars(0, uart_spi_testbench);

        #200 rst = 0;
        #200 start_uart_tx = 1;
        #100 start_uart_tx = 0;

        wait (bridge.spi_done);
        #500;

        $display("[UART→Bridge] Sent: %h", uart_tx_data);
        $display("[SPI Master] Received: %h", spi_rx_data);
        $display("[SPI Slave] Received: %h", slave_data_out);
        $finish;
    end
endmodule

wave.vcd
$date
	Mon Jul 14 19:23:55 2025
$end
$version
	Icarus Verilog
$end
$timescale
	1ps
$end
$scope module uart_spi_testbench $end
$var wire 1 ! cs $end
$var wire 1 " miso $end
$var wire 1 # mosi $end
$var wire 1 $ sclk $end
$var wire 8 % slave_data_out [7:0] $end
$var wire 1 & spi_done $end
$var wire 8 ' spi_rx_data [7:0] $end
$var wire 1 ( spi_start $end
$var wire 8 ) spi_tx_data [7:0] $end
$var wire 1 * tx_busy $end
$var wire 8 + tx_data [7:0] $end
$var wire 1 , tx_line $end
$var wire 1 - tx_start $end
$var wire 8 . uart_data_rx [7:0] $end
$var wire 1 / uart_done_rx $end
$var wire 1 0 uart_tx_line $end
$var reg 1 1 clk $end
$var reg 1 2 rst $end
$var reg 1 3 start_uart_tx $end
$var reg 1 4 uart_rx_line $end
$var reg 8 5 uart_tx_data [7:0] $end
$scope module uart_sender $end
$var wire 1 6 clk $end
$var wire 8 7 data_in [7:0] $end
$var wire 1 8 rst $end
$var wire 1 9 start $end
$var reg 4 : bit_index [3:0] $end
$var reg 1 ; busy $end
$var reg 16 < clk_count [15:0] $end
$var reg 1 = sending $end
$var reg 1 > tx $end
$var reg 10 ? tx_shift [9:0] $end
$upscope $end
$scope module uart_receiver $end
$var wire 1 6 clk $end
$var wire 1 8 rst $end
$var wire 1 @ rx $end
$var reg 4 A bit_index [3:0] $end
$var reg 16 B clk_count [15:0] $end
$var reg 8 C data_out [7:0] $end
$var reg 1 D done $end
$var reg 1 E receiving $end
$var reg 8 F rx_shift [7:0] $end
$var reg 2 G state [1:0] $end
$upscope $end
$scope module spi_master_inst $end
$var wire 1 6 clk $end
$var wire 1 " miso $end
$var wire 8 H mosi_data_in [7:0] $end
$var wire 1 8 rst $end
$var wire 1 ( start $end
$var reg 3 I bit_cnt [2:0] $end
$var reg 2 J clk_div [1:0] $end
$var reg 1 K cs $end
$var reg 1 L done $end
$var reg 8 M miso_data_out [7:0] $end
$var reg 1 N mosi $end
$var reg 1 O sclk $end
$var reg 8 P shift_reg_rx [7:0] $end
$var reg 8 Q shift_reg_tx [7:0] $end
$var reg 3 R state [2:0] $end
$upscope $end
$scope module spi_slave_inst $end
$var wire 1 6 clk $end
$var wire 1 ! cs $end
$var wire 1 # mosi $end
$var wire 1 8 rst $end
$var wire 1 $ sclk $end
$var reg 3 S bit_cnt [2:0] $end
$var reg 8 T data_out [7:0] $end
$var reg 1 U miso $end
$var reg 8 V shift_reg_rx [7:0] $end
$var reg 8 W shift_reg_tx [7:0] $end
$upscope $end
$scope module bridge $end
$var wire 1 6 clk $end
$var wire 1 8 rst $end
$var wire 1 & spi_done $end
$var wire 8 X spi_rx_data [7:0] $end
$var wire 1 * tx_busy $end
$var wire 8 Y uart_data [7:0] $end
$var wire 1 / uart_done $end
$var reg 2 Z next_state [1:0] $end
$var reg 1 [ spi_start $end
$var reg 8 \ spi_tx_data [7:0] $end
$var reg 2 ] state [1:0] $end
$var reg 8 ^ tx_data [7:0] $end
$var reg 1 _ tx_start $end
$upscope $end
$scope module uart_echo $end
$var wire 1 6 clk $end
$var wire 8 ` data_in [7:0] $end
$var wire 1 8 rst $end
$var wire 1 - start $end
$var reg 4 a bit_index [3:0] $end
$var reg 1 b busy $end
$var reg 16 c clk_count [15:0] $end
$var reg 1 d sending $end
$var reg 1 e tx $end
$var reg 10 f tx_shift [9:0] $end
$upscope $end
$upscope $end
$enddefinitions $end
#0
$dumpvars
b1111111111 f
1e
0d
b0 c
0b
b0 a
bx `
0_
bx ^
b0 ]
bx \
0[
b0 Z
b0 Y
b0 X
b10100101 W
b0 V
0U
b0 T
b0 S
b0 R
b0 Q
b0 P
0O
0N
b0 M
0L
1K
b0 J
b0 I
bx H
b0 G
b0 F
0E
0D
b0 C
b0 B
b0 A
1@
b1111111111 ?
1>
0=
b0 <
0;
b0 :
09
18
b111100 7
06
b111100 5
14
03
12
01
10
0/
b0 .
0-
1,
bx +
0*
bx )
0(
b0 '
0&
b0 %
0$
0#
0"
1!
$end
#50000
11
16
#100000
01
06
#150000
11
16
#200000
01
06
02
08
#250000
b1 J
11
16
#300000
01
06
#350000
b10 J
11
16
#400000
01
06
13
19
#450000
b11 J
1=
1;
x*
b1001111000 ?
11
16
#500000
01
06
03
09
#550000
b1 <
b0 J
11
16
#600000
01
06
#650000
b1 J
b10 <
11
16
#700000
01
06
#750000
b11 <
b10 J
11
16
#800000
01
06
#850000
b11 J
b100 <
11
16
#900000
01
06
#950000
b101 <
b0 J
11
16
#1000000
01
06
#1050000
b1 J
b110 <
11
16
#1100000
01
06
#1150000
b111 <
b10 J
11
16
#1200000
01
06
#1250000
b11 J
b1000 <
11
16
#1300000
01
06
#1350000
b1001 <
b0 J
11
16
#1400000
01
06
#1450000
b1 J
b1010 <
11
16
#1500000
01
06
#1550000
b1011 <
b10 J
11
16
#1600000
01
06
#1650000
b11 J
b1100 <
11
16
#1700000
01
06
#1750000
b1101 <
b0 J
11
16
#1800000
01
06
#1850000
b1 J
b1110 <
11
16
#1900000
01
06
#1950000
b1111 <
b10 J
11
16
#2000000
01
06
#2050000
b11 J
b10000 <
11
16
#2100000
01
06
#2150000
b10001 <
b0 J
11
16
#2200000
01
06
#2250000
b1 J
b10010 <
11
16
#2300000
01
06
#2350000
b10011 <
b10 J
11
16
#2400000
01
06
#2450000
b11 J
b10100 <
11
16
#2500000
01
06
#2550000
b10101 <
b0 J
11
16
#2600000
01
06
#2650000
b1 J
b10110 <
11
16
#2700000
01
06
#2750000
b10111 <
b10 J
11
16
#2800000
01
06
#2850000
b11 J
b11000 <
11
16
#2900000
01
06
#2950000
b11001 <
b0 J
11
16
#3000000
01
06
#3050000
b1 J
b11010 <
11
16
#3100000
01
06
#3150000
b11011 <
b10 J
11
16
#3200000
01
06
#3250000
b11 J
b11100 <
11
16
#3300000
01
06
#3350000
b11101 <
b0 J
11
16
#3400000
01
06
#3450000
b1 J
b11110 <
11
16
#3500000
01
06
#3550000
b11111 <
b10 J
11
16
#3600000
01
06
#3650000
b11 J
b100000 <
11
16
#3700000
01
06
#3750000
b100001 <
b0 J
11
16
#3800000
01
06
#3850000
b1 J
b100010 <
11
16
#3900000
01
06
#3950000
b100011 <
b10 J
11
16
#4000000
01
06
#4050000
b11 J
b100100 <
11
16
#4100000
01
06
#4150000
b100101 <
b0 J
11
16
#4200000
01
06
#4250000
b1 J
b100110 <
11
16
#4300000
01
06
#4350000
b100111 <
b10 J
11
16
#4400000
01
06
#4450000
b11 J
b101000 <
11
16
#4500000
01
06
#4550000
b101001 <
b0 J
11
16
#4600000
01
06
#4650000
b1 J
b101010 <
11
16
#4700000
01
06
#4750000
b101011 <
b10 J
11
16
#4800000
01
06
#4850000
b11 J
b101100 <
11
16
#4900000
01
06
#4950000
b101101 <
b0 J
11
16
#5000000
01
06
#5050000
b1 J
b101110 <
11
16
#5100000
01
06
#5150000
b101111 <
b10 J
11
16
#5200000
01
06
#5250000
b11 J
b110000 <
11
16
#5300000
01
06
#5350000
b110001 <
b0 J
11
16
#5400000
01
06
#5450000
b1 J
b110010 <
11
16
#5500000
01
06
#5550000
b110011 <
b10 J
11
16
#5600000
01
06
#5650000
b11 J
b110100 <
11
16
#5700000
01
06
#5750000
b110101 <
b0 J
11
16
#5800000
01
06
#5850000
b1 J
b110110 <
11
16
#5900000
01
06
#5950000
b110111 <
b10 J
11
16
#6000000
01
06
#6050000
b11 J
b111000 <
11
16
#6100000
01
06
#6150000
b111001 <
b0 J
11
16
#6200000
01
06
#6250000
b1 J
b111010 <
11
16
#6300000
01
06
#6350000
b111011 <
b10 J
11
16
#6400000
01
06
#6450000
b11 J
b111100 <
11
16
#6500000
01
06
#6550000
b111101 <
b0 J
11
16
#6600000
01
06
#6650000
b1 J
b111110 <
11
16
#6700000
01
06
#6750000
b111111 <
b10 J
11
16
#6800000
01
06
#6850000
b11 J
b1000000 <
11
16
#6900000
01
06
#6950000
b1000001 <
b0 J
11
16
#7000000
01
06
#7050000
b1 J
b1000010 <
11
16
#7100000
01
06
#7150000
b1000011 <
b10 J
11
16
#7200000
01
06
#7250000
b11 J
b1000100 <
11
16
#7300000
01
06
#7350000
b1000101 <
b0 J
11
16
#7400000
01
06
#7450000
b1 J
b1000110 <
11
16
#7500000
01
06
#7550000
b1000111 <
b10 J
11
16
#7600000
01
06
#7650000
b11 J
b1001000 <
11
16
#7700000
01
06
#7750000
b1001001 <
b0 J
11
16
#7800000
01
06
#7850000
b1 J
b1001010 <
11
16
#7900000
01
06
#7950000
b1001011 <
b10 J
11
16
#8000000
01
06
#8050000
b11 J
b1001100 <
11
16
#8100000
01
06
#8150000
b1001101 <
b0 J
11
16
#8200000
01
06
#8250000
b1 J
b1001110 <
11
16
#8300000
01
06
#8350000
b1001111 <
b10 J
11
16
#8400000
01
06
#8450000
b11 J
b1010000 <
11
16
#8500000
01
06
#8550000
b1010001 <
b0 J
11
16
#8600000
01
06
#8650000
b1 J
b1010010 <
11
16
#8700000
01
06
#8750000
b1010011 <
b10 J
11
16
#8800000
01
06
#8850000
b11 J
b1010100 <
11
16
#8900000
01
06
#8950000
b1010101 <
b0 J
11
16
#9000000
01
06
#9050000
b1 J
b1010110 <
11
16
#9100000
01
06
#9150000
b1 :
0>
00
b0 <
b10 J
11
16
#9200000
01
06
#9250000
b11 J
b1 <
04
0@
11
16
#9300000
01
06
#9350000
b10 <
b1 G
b101011 B
b0 J
11
16
#9400000
01
06
#9450000
b1 J
b101010 B
b11 <
11
16
#9500000
01
06
#9550000
b100 <
b101001 B
b10 J
11
16
#9600000
01
06
#9650000
b11 J
b101000 B
b101 <
11
16
#9700000
01
06
#9750000
b110 <
b100111 B
b0 J
11
16
#9800000
01
06
#9850000
b1 J
b100110 B
b111 <
11
16
#9900000
01
06
#9950000
b1000 <
b100101 B
b10 J
11
16
#10000000
01
06
#10050000
b11 J
b100100 B
b1001 <
11
16
#10100000
01
06
#10150000
b1010 <
b100011 B
b0 J
11
16
#10200000
01
06
#10250000
b1 J
b100010 B
b1011 <
11
16
#10300000
01
06
#10350000
b1100 <
b100001 B
b10 J
11
16
#10400000
01
06
#10450000
b11 J
b100000 B
b1101 <
11
16
#10500000
01
06
#10550000
b1110 <
b11111 B
b0 J
11
16
#10600000
01
06
#10650000
b1 J
b11110 B
b1111 <
11
16
#10700000
01
06
#10750000
b10000 <
b11101 B
b10 J
11
16
#10800000
01
06
#10850000
b11 J
b11100 B
b10001 <
11
16
#10900000
01
06
#10950000
b10010 <
b11011 B
b0 J
11
16
#11000000
01
06
#11050000
b1 J
b11010 B
b10011 <
11
16
#11100000
01
06
#11150000
b10100 <
b11001 B
b10 J
11
16
#11200000
01
06
#11250000
b11 J
b11000 B
b10101 <
11
16
#11300000
01
06
#11350000
b10110 <
b10111 B
b0 J
11
16
#11400000
01
06
#11450000
b1 J
b10110 B
b10111 <
11
16
#11500000
01
06
#11550000
b11000 <
b10101 B
b10 J
11
16
#11600000
01
06
#11650000
b11 J
b10100 B
b11001 <
11
16
#11700000
01
06
#11750000
b11010 <
b10011 B
b0 J
11
16
#11800000
01
06
#11850000
b1 J
b10010 B
b11011 <
11
16
#11900000
01
06
#11950000
b11100 <
b10001 B
b10 J
11
16
#12000000
01
06
#12050000
b11 J
b10000 B
b11101 <
11
16
#12100000
01
06
#12150000
b11110 <
b1111 B
b0 J
11
16
#12200000
01
06
#12250000
b1 J
b1110 B
b11111 <
11
16
#12300000
01
06
#12350000
b100000 <
b1101 B
b10 J
11
16
#12400000
01
06
#12450000
b11 J
b1100 B
b100001 <
11
16
#12500000
01
06
#12550000
b100010 <
b1011 B
b0 J
11
16
#12600000
01
06
#12650000
b1 J
b1010 B
b100011 <
11
16
#12700000
01
06
#12750000
b100100 <
b1001 B
b10 J
11
16
#12800000
01
06
#12850000
b11 J
b1000 B
b100101 <
11
16
#12900000
01
06
#12950000
b100110 <
b111 B
b0 J
11
16
#13000000
01
06
#13050000
b1 J
b110 B
b100111 <
11
16
#13100000
01
06
#13150000
b101000 <
b101 B
b10 J
11
16
#13200000
01
06
#13250000
b11 J
b100 B
b101001 <
11
16
#13300000
01
06
#13350000
b101010 <
b11 B
b0 J
11
16
#13400000
01
06
#13450000
b1 J
b10 B
b101011 <
11
16
#13500000
01
06
#13550000
b101100 <
b1 B
b10 J
11
16
#13600000
01
06
#13650000
b11 J
b0 B
b101101 <
11
16
#13700000
01
06
#13750000
b101110 <
b1010110 B
b10 G
b0 J
11
16
#13800000
01
06
#13850000
b1 J
b1010101 B
b101111 <
11
16
#13900000
01
06
#13950000
b110000 <
b1010100 B
b10 J
11
16
#14000000
01
06
#14050000
b11 J
b1010011 B
b110001 <
11
16
#14100000
01
06
#14150000
b110010 <
b1010010 B
b0 J
11
16
#14200000
01
06
#14250000
b1 J
b1010001 B
b110011 <
11
16
#14300000
01
06
#14350000
b110100 <
b1010000 B
b10 J
11
16
#14400000
01
06
#14450000
b11 J
b1001111 B
b110101 <
11
16
#14500000
01
06
#14550000
b110110 <
b1001110 B
b0 J
11
16
#14600000
01
06
#14650000
b1 J
b1001101 B
b110111 <
11
16
#14700000
01
06
#14750000
b111000 <
b1001100 B
b10 J
11
16
#14800000
01
06
#14850000
b11 J
b1001011 B
b111001 <
11
16
#14900000
01
06
#14950000
b111010 <
b1001010 B
b0 J
11
16
#15000000
01
06
#15050000
b1 J
b1001001 B
b111011 <
11
16
#15100000
01
06
#15150000
b111100 <
b1001000 B
b10 J
11
16
#15200000
01
06
#15250000
b11 J
b1000111 B
b111101 <
11
16
#15300000
01
06
#15350000
b111110 <
b1000110 B
b0 J
11
16
#15400000
01
06
#15450000
b1 J
b1000101 B
b111111 <
11
16
#15500000
01
06
#15550000
b1000000 <
b1000100 B
b10 J
11
16
#15600000
01
06
#15650000
b11 J
b1000011 B
b1000001 <
11
16
#15700000
01
06
#15750000
b1000010 <
b1000010 B
b0 J
11
16
#15800000
01
06
#15850000
b1 J
b1000001 B
b1000011 <
11
16
#15900000
01
06
#15950000
b1000100 <
b1000000 B
b10 J
11
16
#16000000
01
06
#16050000
b11 J
b111111 B
b1000101 <
11
16
#16100000
01
06
#16150000
b1000110 <
b111110 B
b0 J
11
16
#16200000
01
06
#16250000
b1 J
b111101 B
b1000111 <
11
16
#16300000
01
06
#16350000
b1001000 <
b111100 B
b10 J
11
16
#16400000
01
06
#16450000
b11 J
b111011 B
b1001001 <
11
16
#16500000
01
06
#16550000
b1001010 <
b111010 B
b0 J
11
16
#16600000
01
06
#16650000
b1 J
b111001 B
b1001011 <
11
16
#16700000
01
06
#16750000
b1001100 <
b111000 B
b10 J
11
16
#16800000
01
06
#16850000
b11 J
b110111 B
b1001101 <
11
16
#16900000
01
06
#16950000
b1001110 <
b110110 B
b0 J
11
16
#17000000
01
06
#17050000
b1 J
b110101 B
b1001111 <
11
16
#17100000
01
06
#17150000
b1010000 <
b110100 B
b10 J
11
16
#17200000
01
06
#17250000
b11 J
b110011 B
b1010001 <
11
16
#17300000
01
06
#17350000
b1010010 <
b110010 B
b0 J
11
16
#17400000
01
06
#17450000
b1 J
b110001 B
b1010011 <
11
16
#17500000
01
06
#17550000
b1010100 <
b110000 B
b10 J
11
16
#17600000
01
06
#17650000
b11 J
b101111 B
b1010101 <
11
16
#17700000
01
06
#17750000
b1010110 <
b101110 B
b0 J
11
16
#17800000
01
06
#17850000
b1 J
b101101 B
b10 :
b0 <
11
16
#17900000
01
06
#17950000
b1 <
b101100 B
b10 J
11
16
#18000000
01
06
#18050000
b11 J
b101011 B
b10 <
11
16
#18100000
01
06
#18150000
b11 <
b101010 B
b0 J
11
16
#18200000
01
06
#18250000
b1 J
b101001 B
b100 <
11
16
#18300000
01
06
#18350000
b101 <
b101000 B
b10 J
11
16
#18400000
01
06
#18450000
b11 J
b100111 B
b110 <
11
16
#18500000
01
06
#18550000
b111 <
b100110 B
b0 J
11
16
#18600000
01
06
#18650000
b1 J
b100101 B
b1000 <
11
16
#18700000
01
06
#18750000
b1001 <
b100100 B
b10 J
11
16
#18800000
01
06
#18850000
b11 J
b100011 B
b1010 <
11
16
#18900000
01
06
#18950000
b1011 <
b100010 B
b0 J
11
16
#19000000
01
06
#19050000
b1 J
b100001 B
b1100 <
11
16
#19100000
01
06
#19150000
b1101 <
b100000 B
b10 J
11
16
#19200000
01
06
#19250000
b11 J
b11111 B
b1110 <
11
16
#19300000
01
06
#19350000
b1111 <
b11110 B
b0 J
11
16
#19400000
01
06
#19450000
b1 J
b11101 B
b10000 <
11
16
#19500000
01
06
#19550000
b10001 <
b11100 B
b10 J
11
16
#19600000
01
06
#19650000
b11 J
b11011 B
b10010 <
11
16
#19700000
01
06
#19750000
b10011 <
b11010 B
b0 J
11
16
#19800000
01
06
#19850000
b1 J
b11001 B
b10100 <
11
16
#19900000
01
06
#19950000
b10101 <
b11000 B
b10 J
11
16
#20000000
01
06
#20050000
b11 J
b10111 B
b10110 <
11
16
#20100000
01
06
#20150000
b10111 <
b10110 B
b0 J
11
16
#20200000
01
06
#20250000
b1 J
b10101 B
b11000 <
11
16
#20300000
01
06
#20350000
b11001 <
b10100 B
b10 J
11
16
#20400000
01
06
#20450000
b11 J
b10011 B
b11010 <
11
16
#20500000
01
06
#20550000
b11011 <
b10010 B
b0 J
11
16
#20600000
01
06
#20650000
b1 J
b10001 B
b11100 <
11
16
#20700000
01
06
#20750000
b11101 <
b10000 B
b10 J
11
16
#20800000
01
06
#20850000
b11 J
b1111 B
b11110 <
11
16
#20900000
01
06
#20950000
b11111 <
b1110 B
b0 J
11
16
#21000000
01
06
#21050000
b1 J
b1101 B
b100000 <
11
16
#21100000
01
06
#21150000
b100001 <
b1100 B
b10 J
11
16
#21200000
01
06
#21250000
b11 J
b1011 B
b100010 <
11
16
#21300000
01
06
#21350000
b100011 <
b1010 B
b0 J
11
16
#21400000
01
06
#21450000
b1 J
b1001 B
b100100 <
11
16
#21500000
01
06
#21550000
b100101 <
b1000 B
b10 J
11
16
#21600000
01
06
#21650000
b11 J
b111 B
b100110 <
11
16
#21700000
01
06
#21750000
b100111 <
b110 B
b0 J
11
16
#21800000
01
06
#21850000
b1 J
b101 B
b101000 <
11
16
#21900000
01
06
#21950000
b101001 <
b100 B
b10 J
11
16
#22000000
01
06
#22050000
b11 J
b11 B
b101010 <
11
16
#22100000
01
06
#22150000
b101011 <
b10 B
b0 J
11
16
#22200000
01
06
#22250000
b1 J
b1 B
b101100 <
11
16
#22300000
01
06
#22350000
b101101 <
b0 B
b10 J
11
16
#22400000
01
06
#22450000
b11 J
b1010110 B
b1 A
b0 F
b101110 <
11
16
#22500000
01
06
#22550000
b101111 <
b1010101 B
b0 J
11
16
#22600000
01
06
#22650000
b1 J
b1010100 B
b110000 <
11
16
#22700000
01
06
#22750000
b110001 <
b1010011 B
b10 J
11
16
#22800000
01
06
#22850000
b11 J
b1010010 B
b110010 <
11
16
#22900000
01
06
#22950000
b110011 <
b1010001 B
b0 J
11
16
#23000000
01
06
#23050000
b1 J
b1010000 B
b110100 <
11
16
#23100000
01
06
#23150000
b110101 <
b1001111 B
b10 J
11
16
#23200000
01
06
#23250000
b11 J
b1001110 B
b110110 <
11
16
#23300000
01
06
#23350000
b110111 <
b1001101 B
b0 J
11
16
#23400000
01
06
#23450000
b1 J
b1001100 B
b111000 <
11
16
#23500000
01
06
#23550000
b111001 <
b1001011 B
b10 J
11
16
#23600000
01
06
#23650000
b11 J
b1001010 B
b111010 <
11
16
#23700000
01
06
#23750000
b111011 <
b1001001 B
b0 J
11
16
#23800000
01
06
#23850000
b1 J
b1001000 B
b111100 <
11
16
#23900000
01
06
#23950000
b111101 <
b1000111 B
b10 J
11
16
#24000000
01
06
#24050000
b11 J
b1000110 B
b111110 <
11
16
#24100000
01
06
#24150000
b111111 <
b1000101 B
b0 J
11
16
#24200000
01
06
#24250000
b1 J
b1000100 B
b1000000 <
11
16
#24300000
01
06
#24350000
b1000001 <
b1000011 B
b10 J
11
16
#24400000
01
06
#24450000
b11 J
b1000010 B
b1000010 <
11
16
#24500000
01
06
#24550000
b1000011 <
b1000001 B
b0 J
11
16
#24600000
01
06
#24650000
b1 J
b1000000 B
b1000100 <
11
16
#24700000
01
06
#24750000
b1000101 <
b111111 B
b10 J
11
16
#24800000
01
06
#24850000
b11 J
b111110 B
b1000110 <
11
16
#24900000
01
06
#24950000
b1000111 <
b111101 B
b0 J
11
16
#25000000
01
06
#25050000
b1 J
b111100 B
b1001000 <
11
16
#25100000
01
06
#25150000
b1001001 <
b111011 B
b10 J
11
16
#25200000
01
06
#25250000
b11 J
b111010 B
b1001010 <
11
16
#25300000
01
06
